element_sci_api/__init__.py
element_sci_api/api/__init__.py
element_sci_api/api/websocket_base.py
element_sci_api/app/__init__.py
element_sci_api/app/file_manager.py
element_sci_api/app/sci_app.py
element_sci_api/components/__init__.py
element_sci_api/components/base/__init__.py
element_sci_api/components/base/component_base.py
element_sci_api/components/base/dragging_container/__init__.py
element_sci_api/components/base/dragging_container/dragging_container.py
element_sci_api/components/dynamic_charts/__init__.py
element_sci_api/components/dynamic_charts/charts.py
element_sci_api/components/dynamic_charts/data_visualization_screen.py
element_sci_api/components/dynamic_form/__init__.py
element_sci_api/components/dynamic_form/dynamic_form.py
element_sci_api/components/dynamic_form/params.py
element_sci_api/components/local_directory_selector/__init__.py
element_sci_api/components/local_directory_selector/local_directory_selector.py
element_sci_api/components/remote_connection/__init__.py
element_sci_api/components/remote_connection/rdp_client.py
element_sci_api/components/tables/__init__.py
element_sci_api/components/tables/table_browser.py
element_sci_api/utils/__init__.py
element_sci_api/utils/files.py
element_sci_api-0.1.0.dist-info/METADATA
element_sci_api-0.1.0.dist-info/WHEEL
element_sci_api-0.1.0.dist-info/top_level.txt
element_sci_api-0.1.0.dist-info/RECORD
