Metadata-Version: 2.1
Name: element_sci_api
Version: 0.1.0
Requires-Python: >=3.8
Requires-Dist: flask
Requires-Dist: flask-sock
Requires-Dist: sqlalchemy
Requires-Dist: pyecharts
Requires-Dist: dataclasses-json
